dna_audit_tool/__init__.py
dna_audit_tool/main.py
dna_audit_tool/aws_services/__init__.py
dna_audit_tool/aws_services/api_gateway/__init__.py
dna_audit_tool/aws_services/api_gateway/api_gateway_constants.py
dna_audit_tool/aws_services/api_gateway/api_gateway_service.py
dna_audit_tool/aws_services/dat_lambda/__init__.py
dna_audit_tool/aws_services/dat_lambda/lambda_constants.py
dna_audit_tool/aws_services/dat_lambda/lambda_service.py
dna_audit_tool/aws_services/dynamodb/__init__.py
dna_audit_tool/aws_services/dynamodb/dynamodb_constants.py
dna_audit_tool/aws_services/dynamodb/dynamodb_service.py
dna_audit_tool/aws_services/emr/__init__.py
dna_audit_tool/aws_services/emr/emr_constants.py
dna_audit_tool/aws_services/emr/emr_service.py
dna_audit_tool/aws_services/fargate/__init__.py
dna_audit_tool/aws_services/fargate/fargate_constants.py
dna_audit_tool/aws_services/fargate/fargate_service.py
dna_audit_tool/aws_services/glue/__init__.py
dna_audit_tool/aws_services/glue/glue_constants.py
dna_audit_tool/aws_services/glue/glue_service.py
dna_audit_tool/aws_services/kinesis_firehose/__init__.py
dna_audit_tool/aws_services/kinesis_firehose/firehose_constants.py
dna_audit_tool/aws_services/kinesis_firehose/kinesis_firehose_service.py
dna_audit_tool/aws_services/kinesis_stream/__init__.py
dna_audit_tool/aws_services/kinesis_stream/kinesis_stream_constants.py
dna_audit_tool/aws_services/kinesis_stream/kinesis_stream_service.py
dna_audit_tool/aws_services/rds/__init__.py
dna_audit_tool/aws_services/rds/rds_constants.py
dna_audit_tool/aws_services/rds/rds_service.py
dna_audit_tool/aws_services/redshift/__init__.py
dna_audit_tool/aws_services/redshift/redshift_constants.py
dna_audit_tool/aws_services/redshift/redshift_service.py
dna_audit_tool/aws_services/s3/__init__.py
dna_audit_tool/aws_services/s3/s3_constants.py
dna_audit_tool/aws_services/s3/s3_service.py
dna_audit_tool/aws_services/sqs/__init__.py
dna_audit_tool/aws_services/sqs/sqs_constants.py
tooltodn-1.10.dist-info/METADATA
tooltodn-1.10.dist-info/WHEEL
tooltodn-1.10.dist-info/entry_points.txt
tooltodn-1.10.dist-info/top_level.txt
tooltodn-1.10.dist-info/RECORD
